{
  "api": "firebase::auth::User::UpdatePhoneNumberCredential",
  "metadata": {
    "type": "public_api",
    "class": "firebase::auth::User",
    "method": "UpdatePhoneNumberCredential",
    "is_static": false,
    "is_virtual": false,
    "relationship": "returns"
  },
  "direct_dependencies": [
    "Future<User>",
    "PhoneAuthCredential",
    "firebase::Future<User>::Future",
    "firebase::auth::(unnamed namespace)::ValidateCurrentUser",
    "firebase::auth::Promise<User>::Fail",
    "firebase::auth::Promise<User>::LastResult",
    "firebase::auth::Promise<User>::Promise",
    "firebase::auth::Promise<User>::~Promise"
  ],
  "transitive_dependencies": [
    "AuthData",
    "AuthError",
    "Future<User>",
    "PhoneAuthCredential",
    "Promise<User>",
    "ReferenceCountedFutureImpl",
    "User",
    "UserInfoInterface",
    "char",
    "firebase::Future<User>::Future",
    "firebase::Future<User>::operator=",
    "firebase::Future<User>::~Future",
    "firebase::FutureBase::FutureBase",
    "firebase::FutureBase::~FutureBase",
    "firebase::ReferenceCountedFutureImpl::Complete",
    "firebase::ReferenceCountedFutureImpl::LastResult",
    "firebase::ReferenceCountedFutureImpl::SafeAlloc",
    "firebase::SafeFutureHandle<User>::SafeFutureHandle",
    "firebase::SafeFutureHandle<User>::get",
    "firebase::SafeFutureHandle<User>::~SafeFutureHandle",
    "firebase::auth::(unnamed namespace)::ValidateCurrentUser",
    "firebase::auth::Promise<User>::Fail",
    "firebase::auth::Promise<User>::LastResult",
    "firebase::auth::Promise<User>::Promise",
    "firebase::auth::Promise<User>::~Promise",
    "firebase::auth::User::User",
    "firebase::auth::UserInfoInterface::UserInfoInterface",
    "std::__1::basic_string<char, char_traits<char>, allocator<char>>::basic_string"
  ],
  "dependency_count": 28,
  "direct_dependents": [],
  "implementation_order": [
    "firebase::ReferenceCountedFutureImpl::Complete",
    "firebase::FutureBase::FutureBase",
    "AuthData",
    "PhoneAuthCredential",
    "firebase::SafeFutureHandle<User>::get",
    "firebase::Future<User>::operator=",
    "firebase::FutureBase::~FutureBase",
    "firebase::Future<User>::Future",
    "firebase::SafeFutureHandle<User>::SafeFutureHandle",
    "firebase::ReferenceCountedFutureImpl::LastResult",
    "Promise<User>",
    "AuthError",
    "firebase::SafeFutureHandle<User>::~SafeFutureHandle",
    "char",
    "std::__1::basic_string<char, char_traits<char>, allocator<char>>::basic_string",
    "Future<User>",
    "firebase::ReferenceCountedFutureImpl::SafeAlloc",
    "ReferenceCountedFutureImpl",
    "User",
    "UserInfoInterface",
    "firebase::auth::(unnamed namespace)::ValidateCurrentUser",
    "firebase::Future<User>::~Future",
    "firebase::auth::Promise<User>::Fail",
    "firebase::auth::Promise<User>::LastResult",
    "firebase::auth::UserInfoInterface::UserInfoInterface",
    "firebase::auth::Promise<User>::~Promise",
    "firebase::auth::User::User",
    "firebase::auth::Promise<User>::Promise",
    "firebase::auth::User::UpdatePhoneNumberCredential"
  ]
}