{
  "api": "firebase::auth::User::SendEmailVerificationBeforeUpdatingEmailLastResult",
  "metadata": {
    "type": "public_api",
    "class": "firebase::auth::User",
    "method": "SendEmailVerificationBeforeUpdatingEmailLastResult",
    "is_static": false,
    "is_virtual": false,
    "relationship": "returns"
  },
  "direct_dependencies": [
    "Future<void>",
    "firebase::Future<void>::Future",
    "firebase::ReferenceCountedFutureImpl::LastResult"
  ],
  "transitive_dependencies": [
    "Future<void>",
    "firebase::Future<void>::Future",
    "firebase::ReferenceCountedFutureImpl::LastResult"
  ],
  "dependency_count": 3,
  "direct_dependents": [],
  "implementation_order": [
    "Future<void>",
    "firebase::ReferenceCountedFutureImpl::LastResult",
    "firebase::Future<void>::Future",
    "firebase::auth::User::SendEmailVerificationBeforeUpdatingEmailLastResult"
  ]
}